Metadata-Version: 2.1
Name: mafiaonline.py
Version: 1.0.0
Summary: A library to create Mafia Online bots.
Home-page: https://github.com/Zakovskiy/mafiaonline.py
Author: Zakovskiy
Author-email: gogrugu@gmail.com
License: MIT
Download-URL: https://github.com/Zakovskiy/mafiaonline.py/tarball/master
Keywords: mafia,online,mafiaonline,mafiaonline.py,mafiaonline-bot,tokarev,dottap,api,socket,python,python3,python3.x,zakovskiy,official
Platform: UNKNOWN
